.gitignore
.pylintrc
Jenkinsfile
MANIFEST.in
README.md
requirements.txt
requirements_develop.txt
setup.cfg
setup.py
doc/index.rst
github_publish/__init__.py
github_publish/__main__.py
github_publish/arg_parser.py
github_publish/github_publish.py
github_publish.egg-info/PKG-INFO
github_publish.egg-info/SOURCES.txt
github_publish.egg-info/dependency_links.txt
github_publish.egg-info/requires.txt
github_publish.egg-info/top_level.txt
test/run_all.py
test/test_argparser.py
test/test_github_publish